pydantic_settings/__init__.py
pydantic_settings/main.py
pydantic_settings/sources.py
pydantic_settings/utils.py
pydantic_settings/version.py
pydantic_settings-1.99.dist-info/METADATA
pydantic_settings-1.99.dist-info/WHEEL
pydantic_settings-1.99.dist-info/licenses/LICENSE
pydantic_settings-1.99.dist-info/RECORD
