Metadata-Version: 2.1
Name: pydantic-settings
Version: 1.99
Summary: Settings management using Pydantic
Project-URL: Homepage, https://github.com/pydantic/pydantic-settings
Project-URL: Funding, https://github.com/sponsors/samuelcolvin
Project-URL: Source, https://github.com/pydantic/pydantic-settings
Project-URL: Changelog, https://github.com/pydantic/pydantic-settings/releases
Author-email: Samuel Colvin <s@muelcolvin.com>, Eric Jolibois <em.jolibois@gmail.com>, Hasan Ramezani <hasan.r67@gmail.com>
License: The MIT License (MIT)
License-File: LICENSE
Classifier: Development Status :: 5 - Production/Stable
Classifier: Environment :: Console
Classifier: Environment :: MacOS X
Classifier: Intended Audience :: Developers
Classifier: Intended Audience :: Information Technology
Classifier: Intended Audience :: System Administrators
Classifier: License :: OSI Approved :: MIT License
Classifier: Operating System :: POSIX :: Linux
Classifier: Operating System :: Unix
Classifier: Programming Language :: Python
Classifier: Programming Language :: Python :: 3
Classifier: Programming Language :: Python :: 3 :: Only
Classifier: Programming Language :: Python :: 3.7
Classifier: Programming Language :: Python :: 3.8
Classifier: Programming Language :: Python :: 3.9
Classifier: Programming Language :: Python :: 3.10
Classifier: Programming Language :: Python :: 3.11
Classifier: Topic :: Internet
Classifier: Topic :: Software Development :: Libraries :: Python Modules
Requires-Python: >=3.7
Requires-Dist: pydantic==v2.0a3
Requires-Dist: python-dotenv>=0.21.0
